{
    "menu": {
        "Behind the net": "https:\/\/docs.google.com\/document\/d\/1_UUqGU7V78yi1B_v3kfcyjNGYhUDeaulpRJo7pa3Hjs\/edit?usp=sharing",
        "Man-Computer Symbiosis": "https:\/\/groups.csail.mit.edu\/medg\/people\/psz\/Licklider.html",
        "Fuck Off Google": "https:\/\/projects.interactiefarnhem.nl\/behind-the-net\/reader\/documents\/fuckoffgoogleeng.pdf",
        "How Cybernetics Connects Computing Counterculture and Design": "http:\/\/www.dubberly.com\/articles\/cybernetics-and-counterculture.html",
        "Mother Earth Motherboard": "https:\/\/www.wired.com\/1996\/12\/ffglass\/",
        "The Dawn of the Stupid Network": "http:\/\/www.isen.com\/papers\/Dawnstupid.html",
        "The Black Stack": "http:\/\/www.e-flux.com\/journal\/53\/59883\/the-black-stack\/",
        "At Play On The Field of Ghosts": "https:\/\/howwegettonext.com\/at-play-on-the-field-of-ghosts-905b28acfe33#.3oxhv3vzl",
        "Browserbased": "https:\/\/www.facebook.com\/groups\/browserbased\/",
        "Schedule": "https:\/\/docs.google.com\/document\/d\/1GF4T7gwciFrVveCVxWDTGJtwQlVVk65IYs3lYS2cvjU\/edit",
        "Cable Time Line": "http:\/\/atlantic-cable.com\/\/Cables\/CableTimeLine\/atlantic.htm",
        "Submarine Cable Map": "http:\/\/www.submarinecablemap.com",
        "TAT-14 cable": "http:\/\/www.submarinecablemap.com\/#\/submarine-cable\/tat-14",
        "#ACCELERATE Manifesto": "http:\/\/criticallegalthinking.com\/2013\/05\/14\/accelerate-manifesto-for-an-accelerationist-politics\/",
        "From the Server Farm to the Data Table": "https:\/\/media.ccc.de\/v\/33c3-8412-from_server_farm_to_data_table#video&t=1958",
        "INVISIBLE INFRASTRUCTURES : THE EXCITING LIFE OF INTERNET PACKET": "https:\/\/labs.rs\/en\/packets\/"
    }
}